stardustlib/__init__.py
stardustlib-0.0.1.dist-info/LICENSE
stardustlib-0.0.1.dist-info/WHEEL
stardustlib-0.0.1.dist-info/METADATA
stardustlib-0.0.1.dist-info/RECORD
